{
	"format_version": "1.20.80",
	"minecraft:attachable": {
		"description": {
			"identifier": "std:chestplate_v2_quartz",
			"materials": {
				"default": "armor",
				"enchanted": "armor_enchanted"
			},
			"textures": {
				"default": "textures/models/quartz/armor/quartz_v2",
				  "enchanted": "textures/misc/enchanted_item_glint"
			},
			"geometry": {
				"default": "geometry.quartz_v2_chestaplate"

			},
			"scripts": {
				"parent_setup": "variable.chest_layer_visible = 0.0;"
			},
			"render_controllers": [
				"controller.render.armor"
			]
		}
	}
}